Metadata-Version: 2.1
Name: x-chrismo
Version: 1.1
Summary: Gaussian distributions
Home-page: UNKNOWN
Author: Ayo Mosaku
License: UNKNOWN
Platform: UNKNOWN
